ifrn_estatistica/__init__.py
ifrn_estatistica/descriptive_table.py
ifrn_estatistica/emparn.py
ifrn_estatistica/emparn_old_site.py
ifrn_estatistica/plotting_graphs.py
ifrn_estatistica-0.0.10.dist-info/LICENSE
ifrn_estatistica-0.0.10.dist-info/METADATA
ifrn_estatistica-0.0.10.dist-info/WHEEL
ifrn_estatistica-0.0.10.dist-info/top_level.txt
ifrn_estatistica-0.0.10.dist-info/RECORD
